Workbook

Sheet Cover
B3: THE DELHIVERY WAY
B4: Delhivery Direct (C2C) : Financial & Valuation Model
B7: Team | C7: The Solvoholics : Nikhil Menaria, Hiyanshu Gupta
B9: Competition | C9: The Delhivery Way : E-Cell, IIT Kharagpur (Preliminary Round, Finalist submission)
B11: Purpose of this workbook | C11: Quantify and stress-test the GTM strategy proposed in the case deck: FPDR customer prioritization, phased rollout (Pilot -> Cluster -> National), and the 'Delhivery Direct' app economics.
B13: Companion analytics project | C13: ML powered logistics analytics platform (LTV prediction, delay forecasting, SLA-breach prediction) ( github.com/kaunnikhil/c2c_logistics_delhivery)
B15: Currency convention | C15: All figures in Indian Rupees (INR). Revenue/cost lines in Rs Lakh (1 Lakh = Rs 100,000) unless stated. Per unit shipment economics in Rs.
A18: WORKBOOK MAP
B20: Assumptions | C20: Market context, segment unit economics, opex, ML layer impact assumptions (all blue inputs)
B21: LTV_Model | C21: 36 month cohort LTV build per FPDR segment + closed-form LTV cross-check + LTV:CAC + payback
B22: Volume_Build | C22: Quarterly (12Q / 3-yr) sender acquisition, active base, shipment volume by segment
B23: PnL | C23: Quarterly & annual P&L for the Delhivery Direct vertical; break-even quarter
B24: DCF_Valuation | C24: Free cash flow build, NPV / IRR of the initiative, terminal value
B25: Sensitivity | C25: LTV:CAC and NPV sensitivity to churn, CAC and WACC/terminal growth
B26: Dashboard | C26: One page executive summary + quantified value of the ML analytics layer
B28: Color key: Blue = hardcoded input/assumption | Black = formula/calculation | Green = link from another sheet

Sheet Assumptions
A1: ASSUMPTIONS
A2: All hardcoded inputs live here : change these to run the model
A4: 1. MARKET CONTEXT (sourced from case deck, Executive Summary slide)
A5: Indian CEP market size, FY25 (Rs Bn) | B5: 879 | F5: Source: case deck, Executive Summary
A6: Market CAGR | B6: 0.1
A7: Delhivery current backend share of C2C-adjacent ecosystem | B7: 0.21 | F7: Midpoint of case deck's stated 20-22% range
A9: 2. FINANCE / VALUATION ASSUMPTIONS
A10: WACC (annual discount rate) | B10: 0.14 | F10: Illustrative : mid-point for an Indian logistics-tech growth initiative
A11: Terminal growth rate (post Year 3) | B11: 0.05
A12: Corporate tax rate | B12: 0.25
A13: Maintenance capex (% of revenue) | B13: 0.02 | F13: App/tech maintenance, device & packaging kit capex
A15: 3. FPDR SEGMENT UNIT ECONOMICS (from case deck's FPDR framework)
A16: Metric | B16: Homepreneurs / Social Sellers | C16: Students & Migrants | D16: C2C Marketplace Sellers
A17: Avg. shipments / active sender / month | B17: 12 | C17: 2 | D17: 0.8
A18: Avg. revenue per shipment (Rs) | B18: 70 | C18: 85 | D18: 95
A19: Avg. variable cost per shipment (Rs)* | B19: 48 | C19: 55 | D19: 68
A20: Contribution margin per shipment (Rs) | B20: =B18-B19 -> 22 | C20: =C18-C19 -> 30 | D20: =D18-D19 -> 27
A21: Contribution margin % | B21: =B20/B18 -> 0.31428571 | C21: =C20/C18 -> 0.35294118 | D21: =D20/D18 -> 0.28421053
A22: Monthly retention rate (active sender) | B22: 0.9 | C22: 0.7 | D22: 0.5
A23: Monthly churn rate | B23: =1-B22 -> 0.1 | C23: =1-C22 -> 0.3 | D23: =1-D22 -> 0.5
A24: Quarterly retention rate | B24: =B22^3 -> 0.729 | C24: =C22^3 -> 0.343 | D24: =D22^3 -> 0.125
A25: CAC per new active sender (Rs) | B25: 350 | C25: 150 | D25: 220
A26: *Variable cost = first/mid-mile linehaul + last-mile delivery + packaging kit + embedded micro-insurance + support/claims handling
A28: 4. OPEX ASSUMPTIONS (Rs Lakh per quarter, by year of build-out)
A29: Metric | B29: Year 1 (Pilot+Cluster) | C29: Year 2 | D29: Year 3
A30: Tech & platform opex / quarter | B30: 25 | C30: 40 | D30: 55
A31: Ops team opex / quarter (CX, BD, packaging SOP audit) | B31: 30 | C31: 55 | D31: 85
A33: 5. ML ANALYTICS LAYER : IMPACT ASSUMPTIONS (links to the companion ML platform)
A34: Baseline claims/damage cost (% of revenue) without proactive intervention | B34: 0.04
A35: Breach-driven claims avoided via SLA-breach prediction model | B35: 0.3 | F35: Share of claims pre-empted because ops is alerted before the SLA is breached
A36: Net claims-cost saving (% of revenue), formula | B36: =B34*B35 -> 0.012
A37: CAC efficiency gain from LTV-model-led spend reallocation | B37: 0.12 | F37: Reduction in blended CAC from directing acquisition spend toward high-predicted-LTV cohorts instead of untargeted spend

Sheet LTV_Model
A1: LTV MODEL: 36-MONTH COHORT BUILD BY FPDR SEGMENT | R1: Monthly discount rate | S1: =(1+Assumptions!B10)^(1/12)-1 -> 0.010978852
A2: Deterministic cohort decay used as the finance layer's input; a production system would swap in the ML platform's per-cohort survival curve
B3: Homepreneurs / Social Sellers | G3: Students & Migrants | L3: C2C Marketplace Sellers
A4: Month (t) | B4: Retention | C4: Monthly CM (Rs) | D4: Discount factor | E4: Discounted CM (Rs) | F4: Cumulative Disc. CM (Rs) | G4: Retention | H4: Monthly CM (Rs) | I4: Discount factor | J4: Discounted CM (Rs) | K4: Cumulative Disc. CM (Rs) | L4: Retention | M4: Monthly CM (Rs) | N4: Discount factor | O4: Discounted CM (Rs) | P4: Cumulative Disc. CM (Rs)
A5: 0 | B5: =Assumptions!$B$22^A5 -> 1 | C5: =Assumptions!$B$17*Assumptions!$B$20*B5 -> 264 | D5: =1/(1+$S$1)^A5 -> 1 | E5: =C5*D5 -> 264 | F5: =E5 -> 264 | G5: =Assumptions!$C$22^A5 -> 1 | H5: =Assumptions!$C$17*Assumptions!$C$20*G5 -> 60 | I5: =1/(1+$S$1)^A5 -> 1 | J5: =H5*I5 -> 60 | K5: =J5 -> 60 | L5: =Assumptions!$D$22^A5 -> 1 | M5: =Assumptions!$D$17*Assumptions!$D$20*L5 -> 21.6 | N5: =1/(1+$S$1)^A5 -> 1 | O5: =M5*N5 -> 21.6 | P5: =O5 -> 21.6
A6: 1 | B6: =Assumptions!$B$22^A6 -> 0.9 | C6: =Assumptions!$B$17*Assumptions!$B$20*B6 -> 237.6 | D6: =1/(1+$S$1)^A6 -> 0.98914037 | E6: =C6*D6 -> 235.01975 | F6: =F5+E6 -> 499.01975 | G6: =Assumptions!$C$22^A6 -> 0.7 | H6: =Assumptions!$C$17*Assumptions!$C$20*G6 -> 42 | I6: =1/(1+$S$1)^A6 -> 0.98914037 | J6: =H6*I6 -> 41.543896 | K6: =K5+J6 -> 101.5439 | L6: =Assumptions!$D$22^A6 -> 0.5 | M6: =Assumptions!$D$17*Assumptions!$D$20*L6 -> 10.8 | N6: =1/(1+$S$1)^A6 -> 0.98914037 | O6: =M6*N6 -> 10.682716 | P6: =P5+O6 -> 32.282716
A7: 2 | B7: =Assumptions!$B$22^A7 -> 0.81 | C7: =Assumptions!$B$17*Assumptions!$B$20*B7 -> 213.84 | D7: =1/(1+$S$1)^A7 -> 0.97839868 | E7: =C7*D7 -> 209.22077 | F7: =F6+E7 -> 708.24053 | G7: =Assumptions!$C$22^A7 -> 0.49 | H7: =Assumptions!$C$17*Assumptions!$C$20*G7 -> 29.4 | I7: =1/(1+$S$1)^A7 -> 0.97839868 | J7: =H7*I7 -> 28.764921 | K7: =K6+J7 -> 130.30882 | L7: =Assumptions!$D$22^A7 -> 0.25 | M7: =Assumptions!$D$17*Assumptions!$D$20*L7 -> 5.4 | N7: =1/(1+$S$1)^A7 -> 0.97839868 | O7: =M7*N7 -> 5.2833529 | P7: =P6+O7 -> 37.566069
A8: 3 | B8: =Assumptions!$B$22^A8 -> 0.729 | C8: =Assumptions!$B$17*Assumptions!$B$20*B8 -> 192.456 | D8: =1/(1+$S$1)^A8 -> 0.96777364 | E8: =C8*D8 -> 186.25384 | F8: =F7+E8 -> 894.49437 | G8: =Assumptions!$C$22^A8 -> 0.343 | H8: =Assumptions!$C$17*Assumptions!$C$20*G8 -> 20.58 | I8: =1/(1+$S$1)^A8 -> 0.96777364 | J8: =H8*I8 -> 19.916781 | K8: =K7+J8 -> 150.2256 | L8: =Assumptions!$D$22^A8 -> 0.125 | M8: =Assumptions!$D$17*Assumptions!$D$20*L8 -> 2.7 | N8: =1/(1+$S$1)^A8 -> 0.96777364 | O8: =M8*N8 -> 2.6129888 | P8: =P7+O8 -> 40.179058
A9: 4 | B9: =Assumptions!$B$22^A9 -> 0.6561 | C9: =Assumptions!$B$17*Assumptions!$B$20*B9 -> 173.2104 | D9: =1/(1+$S$1)^A9 -> 0.95726398 | E9: =C9*D9 -> 165.80808 | F9: =F8+E9 -> 1060.3024 | G9: =Assumptions!$C$22^A9 -> 0.2401 | H9: =Assumptions!$C$17*Assumptions!$C$20*G9 -> 14.406 | I9: =1/(1+$S$1)^A9 -> 0.95726398 | J9: =H9*I9 -> 13.790345 | K9: =K8+J9 -> 164.01594 | L9: =Assumptions!$D$22^A9 -> 0.0625 | M9: =Assumptions!$D$17*Assumptions!$D$20*L9 -> 1.35 | N9: =1/(1+$S$1)^A9 -> 0.95726398 | O9: =M9*N9 -> 1.2923064 | P9: =P8+O9 -> 41.471364
A10: 5 | B10: =Assumptions!$B$22^A10 -> 0.59049 | C10: =Assumptions!$B$17*Assumptions!$B$20*B10 -> 155.88936 | D10: =1/(1+$S$1)^A10 -> 0.94686845 | E10: =C10*D10 -> 147.60672 | F10: =F9+E10 -> 1207.9092 | G10: =Assumptions!$C$22^A10 -> 0.16807 | H10: =Assumptions!$C$17*Assumptions!$C$20*G10 -> 10.0842 | I10: =1/(1+$S$1)^A10 -> 0.94686845 | J10: =H10*I10 -> 9.5484108 | K10: =K9+J10 -> 173.56435 | L10: =Assumptions!$D$22^A10 -> 0.03125 | M10: =Assumptions!$D$17*Assumptions!$D$20*L10 -> 0.675 | N10: =1/(1+$S$1)^A10 -> 0.94686845 | O10: =M10*N10 -> 0.6391362 | P10: =P9+O10 -> 42.1105
A11: 6 | B11: =Assumptions!$B$22^A11 -> 0.531441 | C11: =Assumptions!$B$17*Assumptions!$B$20*B11 -> 140.30042 | D11: =1/(1+$S$1)^A11 -> 0.93658581 | E11: =C11*D11 -> 131.40339 | F11: =F10+E11 -> 1339.3125 | G11: =Assumptions!$C$22^A11 -> 0.117649 | H11: =Assumptions!$C$17*Assumptions!$C$20*G11 -> 7.05894 | I11: =1/(1+$S$1)^A11 -> 0.93658581 | J11: =H11*I11 -> 6.611303 | K11: =K10+J11 -> 180.17566 | L11: =Assumptions!$D$22^A11 -> 0.015625 | M11: =Assumptions!$D$17*Assumptions!$D$20*L11 -> 0.3375 | N11: =1/(1+$S$1)^A11 -> 0.93658581 | O11: =M11*N11 -> 0.31609771 | P11: =P10+O11 -> 42.426598
A12: 7 | B12: =Assumptions!$B$22^A12 -> 0.4782969 | C12: =Assumptions!$B$17*Assumptions!$B$20*B12 -> 126.27038 | D12: =1/(1+$S$1)^A12 -> 0.92641484 | E12: =C12*D12 -> 116.97876 | F12: =F11+E12 -> 1456.2913 | G12: =Assumptions!$C$22^A12 -> 0.0823543 | H12: =Assumptions!$C$17*Assumptions!$C$20*G12 -> 4.941258 | I12: =1/(1+$S$1)^A12 -> 0.92641484 | J12: =H12*I12 -> 4.5776547 | K12: =K11+J12 -> 184.75331 | L12: =Assumptions!$D$22^A12 -> 0.0078125 | M12: =Assumptions!$D$17*Assumptions!$D$20*L12 -> 0.16875 | N12: =1/(1+$S$1)^A12 -> 0.92641484 | O12: =M12*N12 -> 0.1563325 | P12: =P11+O12 -> 42.582931
A13: 8 | B13: =Assumptions!$B$22^A13 -> 0.43046721 | C13: =Assumptions!$B$17*Assumptions!$B$20*B13 -> 113.64334 | D13: =1/(1+$S$1)^A13 -> 0.91635432 | E13: =C13*D13 -> 104.13757 | F13: =F12+E13 -> 1560.4289 | G13: =Assumptions!$C$22^A13 -> 0.05764801 | H13: =Assumptions!$C$17*Assumptions!$C$20*G13 -> 3.4588806 | I13: =1/(1+$S$1)^A13 -> 0.91635432 | J13: =H13*I13 -> 3.1695602 | K13: =K12+J13 -> 187.92287 | L13: =Assumptions!$D$22^A13 -> 0.00390625 | M13: =Assumptions!$D$17*Assumptions!$D$20*L13 -> 0.084375 | N13: =1/(1+$S$1)^A13 -> 0.91635432 | O13: =M13*N13 -> 0.077317396 | P13: =P12+O13 -> 42.660248
A14: 9 | B14: =Assumptions!$B$22^A14 -> 0.38742049 | C14: =Assumptions!$B$17*Assumptions!$B$20*B14 -> 102.27901 | D14: =1/(1+$S$1)^A14 -> 0.90640306 | E14: =C14*D14 -> 92.706006 | F14: =F13+E14 -> 1653.1349 | G14: =Assumptions!$C$22^A14 -> 0.040353607 | H14: =Assumptions!$C$17*Assumptions!$C$20*G14 -> 2.4212164 | I14: =1/(1+$S$1)^A14 -> 0.90640306 | J14: =H14*I14 -> 2.194598 | K14: =K13+J14 -> 190.11747 | L14: =Assumptions!$D$22^A14 -> 0.001953125 | M14: =Assumptions!$D$17*Assumptions!$D$20*L14 -> 0.0421875 | N14: =1/(1+$S$1)^A14 -> 0.90640306 | O14: =M14*N14 -> 0.038238879 | P14: =P13+O14 -> 42.698487
A15: 10 | B15: =Assumptions!$B$22^A15 -> 0.34867844 | C15: =Assumptions!$B$17*Assumptions!$B$20*B15 -> 92.051108 | D15: =1/(1+$S$1)^A15 -> 0.89655986 | E15: =C15*D15 -> 82.529329 | F15: =F14+E15 -> 1735.6642 | G15: =Assumptions!$C$22^A15 -> 0.028247525 | H15: =Assumptions!$C$17*Assumptions!$C$20*G15 -> 1.6948515 | I15: =1/(1+$S$1)^A15 -> 0.89655986 | J15: =H15*I15 -> 1.5195358 | K15: =K14+J15 -> 191.63701 | L15: =Assumptions!$D$22^A15 -> 0.0009765625 | M15: =Assumptions!$D$17*Assumptions!$D$20*L15 -> 0.02109375 | N15: =1/(1+$S$1)^A15 -> 0.89655986 | O15: =M15*N15 -> 0.01891181 | P15: =P14+O15 -> 42.717399
A16: 11 | B16: =Assumptions!$B$22^A16 -> 0.3138106 | C16: =Assumptions!$B$17*Assumptions!$B$20*B16 -> 82.845997 | D16: =1/(1+$S$1)^A16 -> 0.88682355 | E16: =C16*D16 -> 73.469782 | F16: =F15+E16 -> 1809.134 | G16: =Assumptions!$C$22^A16 -> 0.019773267 | H16: =Assumptions!$C$17*Assumptions!$C$20*G16 -> 1.186396 | I16: =1/(1+$S$1)^A16 -> 0.88682355 | J16: =H16*I16 -> 1.052124 | K16: =K15+J16 -> 192.68913 | L16: =Assumptions!$D$22^A16 -> 0.00048828125 | M16: =Assumptions!$D$17*Assumptions!$D$20*L16 -> 0.010546875 | N16: =1/(1+$S$1)^A16 -> 0.88682355 | O16: =M16*N16 -> 0.0093532172 | P16: =P15+O16 -> 42.726752
A17: 12 | B17: =Assumptions!$B$22^A17 -> 0.28242954 | C17: =Assumptions!$B$17*Assumptions!$B$20*B17 -> 74.561398 | D17: =1/(1+$S$1)^A17 -> 0.87719298 | E17: =C17*D17 -> 65.404735 | F17: =F16+E17 -> 1874.5387 | G17: =Assumptions!$C$22^A17 -> 0.013841287 | H17: =Assumptions!$C$17*Assumptions!$C$20*G17 -> 0.83047723 | I17: =1/(1+$S$1)^A17 -> 0.87719298 | J17: =H17*I17 -> 0.7284888 | K17: =K16+J17 -> 193.41762 | L17: =Assumptions!$D$22^A17 -> 0.00024414062 | M17: =Assumptions!$D$17*Assumptions!$D$20*L17 -> 0.0052734375 | N17: =1/(1+$S$1)^A17 -> 0.87719298 | O17: =M17*N17 -> 0.0046258224 | P17: =P16+O17 -> 42.731378
... A40: 35 | B40: =Assumptions!$B$22^A40 -> 0.025031555 | C40: =Assumptions!$B$17*Assumptions!$B$20*B40 -> 6.6083305 | D40: =1/(1+$S$1)^A40 -> 0.68238193 | E40: =C40*D40 -> 4.5094053 | F40: =F39+E40 -> 2368.3787 | G40: =Assumptions!$C$22^A40 -> 3.7881869e-06 | H40: =Assumptions!$C$17*Assumptions!$C$20*G40 -> 0.00022729122 | I40: =1/(1+$S$1)^A40 -> 0.68238193 | J40: =H40*I40 -> 0.00015509942 | K40: =K39+J40 -> 195.05707 | L40: =Assumptions!$D$22^A40 -> 2.910383e-11 | M40: =Assumptions!$D$17*Assumptions!$D$20*L40 -> 6.2864274e-10 | N40: =1/(1+$S$1)^A40 -> 0.68238193 | O40: =M40*N40 -> 4.2897444e-10 | P40: =P39+O40 -> 42.735904
A42: LTV SUMMARY & VALIDATION
A43: LTV — 36-month discounted cohort sum (Rs) | B43: =SUM(E5:E40) -> 2368.3787 | G43: =SUM(J5:J40) -> 195.05707 | L43: =SUM(O5:O40) -> 42.735904
A44: LTV — closed-form infinite-horizon cross-check (Rs) | B44: =(Assumptions!$B$17*Assumptions!$B$20)/(1-Assumptions!$B$22/(1+$S$1)) -> 2404.9484 | F44: Closed form: LTV = CM0 / (1 - retention/(1+i)); cross-checks the truncated 36-month sum above | G44: =(Assumptions!$C$17*Assumptions!$C$20)/(1-Assumptions!$C$22/(1+$S$1)) -> 195.05742 | L44: =(Assumptions!$D$17*Assumptions!$D$20)/(1-Assumptions!$D$22/(1+$S$1)) -> 42.735904
A45: CAC per new active sender (Rs) | B45: =Assumptions!$B$25 -> 350 | G45: =Assumptions!$C$25 -> 150 | L45: =Assumptions!$D$25 -> 220
A46: LTV : CAC ratio (36-month basis) | B46: =B43/B45 -> 6.7667964 | G46: =G43/G45 -> 1.3003804 | L46: =L43/L45 -> 0.19425411
A47: Approx. payback period (months) | B47: =MATCH(B45,F5:F40,1)-1 -> 0 | F47: Month index (0-based) at which cumulative discounted contribution margin first recovers CAC | G47: =MATCH(G45,K5:K40,1)-1 -> 2 | L47: =MATCH(L45,P5:P40,1)-1 -> 35

Sheet Volume_Build
A1: VOLUME BUILD : QUARTERLY ACQUISITION & SHIPMENT VOLUME (3-YEAR / 12-QUARTER)
A2: Phase 1 Pilot (Q1) -> Phase 2 Cluster Expansion (Q2-Q3) -> Phase 3 National Scale (Q4-Q12)
B3: Year 1 (Pilot + Cluster Expansion) | F3: Year 2 (National Scale) | J3: Year 3 (National Scale, mature)
A4: Metric | B4: Q1 | C4: Q2 | D4: Q3 | E4: Q4 | F4: Q5 | G4: Q6 | H4: Q7 | I4: Q8 | J4: Q9 | K4: Q10 | L4: Q11 | M4: Q12
A6: HOMEPRENEURS / SOCIAL SELLERS
A7: New active senders acquired (input) | B7: 3000 | C7: 6000 | D7: 9000 | E7: 12000 | F7: 15000 | G7: 16000 | H7: 17000 | I7: 18000 | J7: 19000 | K7: 20000 | L7: 21000 | M7: 22000
A8: Active senders (end of quarter) | B8: =B7 -> 3000 | C8: =B8*Assumptions!$B$24+C7 -> 8187 | D8: =C8*Assumptions!$B$24+D7 -> 14968.323 | E8: =D8*Assumptions!$B$24+E7 -> 22911.907 | F8: =E8*Assumptions!$B$24+F7 -> 31702.781 | G8: =F8*Assumptions!$B$24+G7 -> 39111.327 | H8: =G8*Assumptions!$B$24+H7 -> 45512.157 | I8: =H8*Assumptions!$B$24+I7 -> 51178.363 | J8: =I8*Assumptions!$B$24+J7 -> 56309.026 | ... M8: =L8*Assumptions!$B$24+M7 -> 69753.091
A9: Shipments in quarter | B9: =B8*Assumptions!$B$17*3 -> 108000 | C9: =C8*Assumptions!$B$17*3 -> 294732 | D9: =D8*Assumptions!$B$17*3 -> 538859.63 | E9: =E8*Assumptions!$B$17*3 -> 824828.67 | F9: =F8*Assumptions!$B$17*3 -> 1141300.1 | G9: =G8*Assumptions!$B$17*3 -> 1408007.8 | H9: =H8*Assumptions!$B$17*3 -> 1638437.7 | I9: =I8*Assumptions!$B$17*3 -> 1842421.1 | ... M9: =M8*Assumptions!$B$17*3 -> 2511111.3
A10: Revenue (Rs Lakh) | B10: =B9*Assumptions!$B$18/100000 -> 75.6 | C10: =C9*Assumptions!$B$18/100000 -> 206.3124 | D10: =D9*Assumptions!$B$18/100000 -> 377.20174 | E10: =E9*Assumptions!$B$18/100000 -> 577.38007 | F10: =F9*Assumptions!$B$18/100000 -> 798.91007 | G10: =G9*Assumptions!$B$18/100000 -> 985.60544 | H10: =H9*Assumptions!$B$18/100000 -> 1146.9064 | I10: =I9*Assumptions!$B$18/100000 -> 1289.6947 | ... M10: =M9*Assumptions!$B$18/100000 -> 1757.7779
A11: Variable cost (Rs Lakh) | B11: =B9*Assumptions!$B$19/100000 -> 51.84 | C11: =C9*Assumptions!$B$19/100000 -> 141.47136 | D11: =D9*Assumptions!$B$19/100000 -> 258.65262 | E11: =E9*Assumptions!$B$19/100000 -> 395.91776 | F11: =F9*Assumptions!$B$19/100000 -> 547.82405 | G11: =G9*Assumptions!$B$19/100000 -> 675.84373 | H11: =H9*Assumptions!$B$19/100000 -> 786.45008 | I11: =I9*Assumptions!$B$19/100000 -> 884.36211 | ... M11: =M9*Assumptions!$B$19/100000 -> 1205.3334
A12: Contribution margin (Rs Lakh) | B12: =B10-B11 -> 23.76 | C12: =C10-C11 -> 64.84104 | D12: =D10-D11 -> 118.54912 | E12: =E10-E11 -> 181.46231 | F12: =F10-F11 -> 251.08602 | G12: =G10-G11 -> 309.76171 | H12: =H10-H11 -> 360.45629 | I12: =I10-I11 -> 405.33263 | ... M12: =M10-M11 -> 552.44448
A13: Marketing / CAC spend (Rs Lakh) | B13: =B7*Assumptions!$B$25/100000 -> 10.5 | C13: =C7*Assumptions!$B$25/100000 -> 21 | D13: =D7*Assumptions!$B$25/100000 -> 31.5 | E13: =E7*Assumptions!$B$25/100000 -> 42 | F13: =F7*Assumptions!$B$25/100000 -> 52.5 | G13: =G7*Assumptions!$B$25/100000 -> 56 | H13: =H7*Assumptions!$B$25/100000 -> 59.5 | I13: =I7*Assumptions!$B$25/100000 -> 63 | ... M13: =M7*Assumptions!$B$25/100000 -> 77
A15: STUDENTS & MIGRANTS
A16: New active senders acquired (input) | B16: 5000 | C16: 3000 | D16: 7000 | E16: 4000 | F16: 8000 | G16: 5000 | H16: 9000 | I16: 6000 | J16: 10000 | K16: 7000 | L16: 11000 | M16: 8000
A17: Active senders (end of quarter) | B17: =B16 -> 5000 | C17: =B17*Assumptions!$C$24+C16 -> 4715 | D17: =C17*Assumptions!$C$24+D16 -> 8617.245 | E17: =D17*Assumptions!$C$24+E16 -> 6955.715 | F17: =E17*Assumptions!$C$24+F16 -> 10385.81 | G17: =F17*Assumptions!$C$24+G16 -> 8562.3329 | H17: =G17*Assumptions!$C$24+H16 -> 11936.88 | I17: =H17*Assumptions!$C$24+I16 -> 10094.35 | J17: =I17*Assumptions!$C$24+J16 -> 13462.362 | ... M17: =L17*Assumptions!$C$24+M16 -> 13139.798
A18: Shipments in quarter | B18: =B17*Assumptions!$C$17*3 -> 30000 | C18: =C17*Assumptions!$C$17*3 -> 28290 | D18: =D17*Assumptions!$C$17*3 -> 51703.47 | E18: =E17*Assumptions!$C$17*3 -> 41734.29 | F18: =F17*Assumptions!$C$17*3 -> 62314.862 | G18: =G17*Assumptions!$C$17*3 -> 51373.998 | H18: =H17*Assumptions!$C$17*3 -> 71621.281 | I18: =I17*Assumptions!$C$17*3 -> 60566.099 | ... M18: =M17*Assumptions!$C$17*3 -> 78838.787
A19: Revenue (Rs Lakh) | B19: =B18*Assumptions!$C$18/100000 -> 25.5 | C19: =C18*Assumptions!$C$18/100000 -> 24.0465 | D19: =D18*Assumptions!$C$18/100000 -> 43.947949 | E19: =E18*Assumptions!$C$18/100000 -> 35.474147 | F19: =F18*Assumptions!$C$18/100000 -> 52.967632 | G19: =G18*Assumptions!$C$18/100000 -> 43.667898 | H19: =H18*Assumptions!$C$18/100000 -> 60.878089 | I19: =I18*Assumptions!$C$18/100000 -> 51.481185 | ... M19: =M18*Assumptions!$C$18/100000 -> 67.012969
A20: Variable cost (Rs Lakh) | B20: =B18*Assumptions!$C$19/100000 -> 16.5 | C20: =C18*Assumptions!$C$19/100000 -> 15.5595 | D20: =D18*Assumptions!$C$19/100000 -> 28.436908 | E20: =E18*Assumptions!$C$19/100000 -> 22.95386 | F20: =F18*Assumptions!$C$19/100000 -> 34.273174 | G20: =G18*Assumptions!$C$19/100000 -> 28.255699 | H20: =H18*Assumptions!$C$19/100000 -> 39.391705 | I20: =I18*Assumptions!$C$19/100000 -> 33.311355 | ... M20: =M18*Assumptions!$C$19/100000 -> 43.361333
A21: Contribution margin (Rs Lakh) | B21: =B19-B20 -> 9 | C21: =C19-C20 -> 8.487 | D21: =D19-D20 -> 15.511041 | E21: =E19-E20 -> 12.520287 | F21: =F19-F20 -> 18.694458 | G21: =G19-G20 -> 15.412199 | H21: =H19-H20 -> 21.486384 | I21: =I19-I20 -> 18.16983 | ... M21: =M19-M20 -> 23.651636
A22: Marketing / CAC spend (Rs Lakh) | B22: =B16*Assumptions!$C$25/100000 -> 7.5 | C22: =C16*Assumptions!$C$25/100000 -> 4.5 | D22: =D16*Assumptions!$C$25/100000 -> 10.5 | E22: =E16*Assumptions!$C$25/100000 -> 6 | F22: =F16*Assumptions!$C$25/100000 -> 12 | G22: =G16*Assumptions!$C$25/100000 -> 7.5 | H22: =H16*Assumptions!$C$25/100000 -> 13.5 | I22: =I16*Assumptions!$C$25/100000 -> 9 | ... M22: =M16*Assumptions!$C$25/100000 -> 12
A24: C2C MARKETPLACE SELLERS
A25: New active senders acquired (input) | B25: 1000 | C25: 1500 | D25: 2000 | E25: 2500 | F25: 3000 | G25: 3500 | H25: 4000 | I25: 4500 | J25: 5000 | K25: 5500 | L25: 6000 | M25: 6500
A26: Active senders (end of quarter) | B26: =B25 -> 1000 | C26: =B26*Assumptions!$D$24+C25 -> 1625 | D26: =C26*Assumptions!$D$24+D25 -> 2203.125 | E26: =D26*Assumptions!$D$24+E25 -> 2775.3906 | F26: =E26*Assumptions!$D$24+F25 -> 3346.9238 | G26: =F26*Assumptions!$D$24+G25 -> 3918.3655 | H26: =G26*Assumptions!$D$24+H25 -> 4489.7957 | I26: =H26*Assumptions!$D$24+I25 -> 5061.2245 | J26: =I26*Assumptions!$D$24+J25 -> 5632.6531 | ... M26: =L26*Assumptions!$D$24+M25 -> 7346.9388
A27: Shipments in quarter | B27: =B26*Assumptions!$D$17*3 -> 2400 | C27: =C26*Assumptions!$D$17*3 -> 3900 | D27: =D26*Assumptions!$D$17*3 -> 5287.5 | E27: =E26*Assumptions!$D$17*3 -> 6660.9375 | F27: =F26*Assumptions!$D$17*3 -> 8032.6172 | G27: =G26*Assumptions!$D$17*3 -> 9404.0771 | H27: =H26*Assumptions!$D$17*3 -> 10775.51 | I27: =I26*Assumptions!$D$17*3 -> 12146.939 | ... M27: =M26*Assumptions!$D$17*3 -> 17632.653
A28: Revenue (Rs Lakh) | B28: =B27*Assumptions!$D$18/100000 -> 2.28 | C28: =C27*Assumptions!$D$18/100000 -> 3.705 | D28: =D27*Assumptions!$D$18/100000 -> 5.023125 | E28: =E27*Assumptions!$D$18/100000 -> 6.3278906 | F28: =F27*Assumptions!$D$18/100000 -> 7.6309863 | G28: =G27*Assumptions!$D$18/100000 -> 8.9338733 | H28: =H27*Assumptions!$D$18/100000 -> 10.236734 | I28: =I27*Assumptions!$D$18/100000 -> 11.539592 | ... M28: =M27*Assumptions!$D$18/100000 -> 16.75102
A29: Variable cost (Rs Lakh) | B29: =B27*Assumptions!$D$19/100000 -> 1.632 | C29: =C27*Assumptions!$D$19/100000 -> 2.652 | D29: =D27*Assumptions!$D$19/100000 -> 3.5955 | E29: =E27*Assumptions!$D$19/100000 -> 4.5294375 | F29: =F27*Assumptions!$D$19/100000 -> 5.4621797 | G29: =G27*Assumptions!$D$19/100000 -> 6.3947725 | H29: =H27*Assumptions!$D$19/100000 -> 7.3273466 | I29: =I27*Assumptions!$D$19/100000 -> 8.2599183 | ... M29: =M27*Assumptions!$D$19/100000 -> 11.990204
A30: Contribution margin (Rs Lakh) | B30: =B28-B29 -> 0.648 | C30: =C28-C29 -> 1.053 | D30: =D28-D29 -> 1.427625 | E30: =E28-E29 -> 1.7984531 | F30: =F28-F29 -> 2.1688066 | G30: =G28-G29 -> 2.5391008 | H30: =H28-H29 -> 2.9093876 | I30: =I28-I29 -> 3.2796735 | ... M30: =M28-M29 -> 4.7608163
A31: Marketing / CAC spend (Rs Lakh) | B31: =B25*Assumptions!$D$25/100000 -> 2.2 | C31: =C25*Assumptions!$D$25/100000 -> 3.3 | D31: =D25*Assumptions!$D$25/100000 -> 4.4 | E31: =E25*Assumptions!$D$25/100000 -> 5.5 | F31: =F25*Assumptions!$D$25/100000 -> 6.6 | G31: =G25*Assumptions!$D$25/100000 -> 7.7 | H31: =H25*Assumptions!$D$25/100000 -> 8.8 | I31: =I25*Assumptions!$D$25/100000 -> 9.9 | ... M31: =M25*Assumptions!$D$25/100000 -> 14.3
A33: TOTAL — DELHIVERY DIRECT (ALL FPDR SEGMENTS)
A34: New active senders acquired | B34: =B7+B16+B25 -> 9000 | C34: =C7+C16+C25 -> 10500 | D34: =D7+D16+D25 -> 18000 | E34: =E7+E16+E25 -> 18500 | F34: =F7+F16+F25 -> 26000 | G34: =G7+G16+G25 -> 24500 | H34: =H7+H16+H25 -> 30000 | I34: =I7+I16+I25 -> 28500 | ... M34: =M7+M16+M25 -> 36500
A35: Active senders (end of quarter) | B35: =B8+B17+B26 -> 9000 | C35: =C8+C17+C26 -> 14527 | D35: =D8+D17+D26 -> 25788.693 | E35: =E8+E17+E26 -> 32643.013 | F35: =F8+F17+F26 -> 45435.515 | G35: =G8+G17+G26 -> 51592.025 | H35: =H8+H17+H26 -> 61938.833 | I35: =I8+I17+I26 -> 66333.937 | ... M35: =M8+M17+M26 -> 90239.827
A36: Shipments in quarter | B36: =B9+B18+B27 -> 140400 | C36: =C9+C18+C27 -> 326922 | D36: =D9+D18+D27 -> 595850.6 | E36: =E9+E18+E27 -> 873223.9 | F36: =F9+F18+F27 -> 1211647.6 | G36: =G9+G18+G27 -> 1468785.8 | H36: =H9+H18+H27 -> 1720834.5 | I36: =I9+I18+I27 -> 1915134.1 | ... M36: =M9+M18+M27 -> 2607582.7
A37: Revenue (Rs Lakh) | B37: =B10+B19+B28 -> 103.38 | C37: =C10+C19+C28 -> 234.0639 | D37: =D10+D19+D28 -> 426.17281 | E37: =E10+E19+E28 -> 619.18211 | F37: =F10+F19+F28 -> 859.50869 | G37: =G10+G19+G28 -> 1038.2072 | H37: =H10+H19+H28 -> 1218.0212 | I37: =I10+I19+I28 -> 1352.7155 | ... M37: =M10+M19+M28 -> 1841.5419
A38: Variable cost (Rs Lakh) | B38: =B11+B20+B29 -> 69.972 | C38: =C11+C20+C29 -> 159.68286 | D38: =D11+D20+D29 -> 290.68503 | E38: =E11+E20+E29 -> 423.40106 | F38: =F11+F20+F29 -> 587.5594 | G38: =G11+G20+G29 -> 710.4942 | H38: =H11+H20+H29 -> 833.16913 | I38: =I11+I20+I29 -> 925.93338 | ... M38: =M11+M20+M29 -> 1260.6849
A39: Contribution margin (Rs Lakh) | B39: =B12+B21+B30 -> 33.408 | C39: =C12+C21+C30 -> 74.38104 | D39: =D12+D21+D30 -> 135.48778 | E39: =E12+E21+E30 -> 195.78105 | F39: =F12+F21+F30 -> 271.94929 | G39: =G12+G21+G30 -> 327.71301 | H39: =H12+H21+H30 -> 384.85206 | I39: =I12+I21+I30 -> 426.78214 | ... M39: =M12+M21+M30 -> 580.85693
A40: Marketing / CAC spend (Rs Lakh) | B40: =B13+B22+B31 -> 20.2 | C40: =C13+C22+C31 -> 28.8 | D40: =D13+D22+D31 -> 46.4 | E40: =E13+E22+E31 -> 53.5 | F40: =F13+F22+F31 -> 71.1 | G40: =G13+G22+G31 -> 71.2 | H40: =H13+H22+H31 -> 81.8 | I40: =I13+I22+I31 -> 81.9 | ... M40: =M13+M22+M31 -> 103.3

Sheet PnL
A1: P&L: DELHIVERY DIRECT (C2C) VERTICAL
A2: Quarterly build, 3-year horizon, showing the quantified contribution of the ML analytics layer
B3: Year 1 | F3: Year 2 | J3: Year 3
A4: Metric | B4: Q1 | C4: Q2 | D4: Q3 | E4: Q4 | F4: Q5 | G4: Q6 | H4: Q7 | I4: Q8 | J4: Q9 | K4: Q10 | L4: Q11 | M4: Q12 | O4: FY1 | P4: FY2 | Q4: FY3
A6: Revenue (Rs Lakh) | B6: =Volume_Build!B37 -> 103.38 | C6: =Volume_Build!C37 -> 234.0639 | D6: =Volume_Build!D37 -> 426.17281 | E6: =Volume_Build!E37 -> 619.18211 | F6: =Volume_Build!F37 -> 859.50869 | G6: =Volume_Build!G37 -> 1038.2072 | H6: =Volume_Build!H37 -> 1218.0212 | I6: =Volume_Build!I37 -> 1352.7155 | ... M6: =Volume_Build!M37 -> 1841.5419 | O6: =SUM(B6:E6) -> 1382.7988 | P6: =SUM(F6:I6) -> 4468.4526 | Q6: =SUM(J6:M6) -> 6696.4616
A7: Variable cost (Rs Lakh) | B7: =Volume_Build!B38 -> 69.972 | C7: =Volume_Build!C38 -> 159.68286 | D7: =Volume_Build!D38 -> 290.68503 | E7: =Volume_Build!E38 -> 423.40106 | F7: =Volume_Build!F38 -> 587.5594 | G7: =Volume_Build!G38 -> 710.4942 | H7: =Volume_Build!H38 -> 833.16913 | I7: =Volume_Build!I38 -> 925.93338 | ... M7: =Volume_Build!M38 -> 1260.6849 | O7: =SUM(B7:E7) -> 943.74095 | P7: =SUM(F7:I7) -> 3057.1561 | Q7: =SUM(J7:M7) -> 4583.1506
A8: Gross contribution margin (Rs Lakh) | B8: =B6-B7 -> 33.408 | C8: =C6-C7 -> 74.38104 | D8: =D6-D7 -> 135.48778 | E8: =E6-E7 -> 195.78105 | F8: =F6-F7 -> 271.94929 | G8: =G6-G7 -> 327.71301 | H8: =H6-H7 -> 384.85206 | I8: =I6-I7 -> 426.78214 | ... M8: =M6-M7 -> 580.85693 | O8: =SUM(B8:E8) -> 439.05787 | P8: =SUM(F8:I8) -> 1411.2965 | Q8: =SUM(J8:M8) -> 2113.3111
A9: (+) Claims-cost saved: SLA-breach prediction model | B9: =B6*Assumptions!$B$36 -> 1.24056 | C9: =C6*Assumptions!$B$36 -> 2.8087668 | D9: =D6*Assumptions!$B$36 -> 5.1140738 | E9: =E6*Assumptions!$B$36 -> 7.4301853 | F9: =F6*Assumptions!$B$36 -> 10.314104 | G9: =G6*Assumptions!$B$36 -> 12.458487 | H9: =H6*Assumptions!$B$36 -> 14.616254 | I9: =I6*Assumptions!$B$36 -> 16.232586 | ... M9: =M6*Assumptions!$B$36 -> 22.098502 | O9: =SUM(B9:E9) -> 16.593586 | P9: =SUM(F9:I9) -> 53.621431 | Q9: =SUM(J9:M9) -> 80.35754
A10: Adjusted contribution margin (Rs Lakh) | B10: =B8+B9 -> 34.64856 | C10: =C8+C9 -> 77.189807 | D10: =D8+D9 -> 140.60186 | E10: =E8+E9 -> 203.21123 | F10: =F8+F9 -> 282.26339 | G10: =G8+G9 -> 340.1715 | H10: =H8+H9 -> 399.46831 | I10: =I8+I9 -> 443.01472 | ... M10: =M8+M9 -> 602.95543 | O10: =SUM(B10:E10) -> 455.65146 | P10: =SUM(F10:I10) -> 1464.9179 | Q10: =SUM(J10:M10) -> 2193.6686
A12: (-) Marketing / CAC spend, net of LTV-model efficiency gain | B12: =Volume_Build!B40*(1-Assumptions!$B$37) -> 17.776 | C12: =Volume_Build!C40*(1-Assumptions!$B$37) -> 25.344 | D12: =Volume_Build!D40*(1-Assumptions!$B$37) -> 40.832 | E12: =Volume_Build!E40*(1-Assumptions!$B$37) -> 47.08 | F12: =Volume_Build!F40*(1-Assumptions!$B$37) -> 62.568 | G12: =Volume_Build!G40*(1-Assumptions!$B$37) -> 62.656 | H12: =Volume_Build!H40*(1-Assumptions!$B$37) -> 71.984 | I12: =Volume_Build!I40*(1-Assumptions!$B$37) -> 72.072 | ... M12: =Volume_Build!M40*(1-Assumptions!$B$37) -> 90.904 | O12: =SUM(B12:E12) -> 131.032 | P12: =SUM(F12:I12) -> 269.28 | Q12: =SUM(J12:M12) -> 344.608
A13: (-) Tech & platform opex | B13: =Assumptions!$B$30 -> 25 | C13: =Assumptions!$B$30 -> 25 | D13: =Assumptions!$B$30 -> 25 | E13: =Assumptions!$B$30 -> 25 | F13: =Assumptions!$C$30 -> 40 | G13: =Assumptions!$C$30 -> 40 | H13: =Assumptions!$C$30 -> 40 | I13: =Assumptions!$C$30 -> 40 | J13: =Assumptions!$D$30 -> 55 | K13: =Assumptions!$D$30 -> 55 | L13: =Assumptions!$D$30 -> 55 | M13: =Assumptions!$D$30 -> 55 | O13: =SUM(B13:E13) -> 100 | P13: =SUM(F13:I13) -> 160 | Q13: =SUM(J13:M13) -> 220
A14: (-) Ops team opex | B14: =Assumptions!$B$31 -> 30 | C14: =Assumptions!$B$31 -> 30 | D14: =Assumptions!$B$31 -> 30 | E14: =Assumptions!$B$31 -> 30 | F14: =Assumptions!$C$31 -> 55 | G14: =Assumptions!$C$31 -> 55 | H14: =Assumptions!$C$31 -> 55 | I14: =Assumptions!$C$31 -> 55 | J14: =Assumptions!$D$31 -> 85 | K14: =Assumptions!$D$31 -> 85 | L14: =Assumptions!$D$31 -> 85 | M14: =Assumptions!$D$31 -> 85 | O14: =SUM(B14:E14) -> 120 | P14: =SUM(F14:I14) -> 220 | Q14: =SUM(J14:M14) -> 340
A15: EBITDA (Rs Lakh) | B15: =B10-B12-B13-B14 -> -38.12744 | C15: =C10-C12-C13-C14 -> -3.1541932 | D15: =D10-D12-D13-D14 -> 44.769858 | E15: =E10-E12-E13-E14 -> 101.13123 | F15: =F10-F12-F13-F14 -> 124.69539 | G15: =G10-G12-G13-G14 -> 182.5155 | H15: =H10-H12-H13-H14 -> 232.48431 | I15: =I10-I12-I13-I14 -> 275.94272 | ... M15: =M10-M12-M13-M14 -> 372.05143 | O15: =SUM(B15:E15) -> 104.61946 | P15: =SUM(F15:I15) -> 815.63792 | Q15: =SUM(J15:M15) -> 1289.0606
A16: EBITDA margin % | B16: =B15/B6 -> -0.36880867 | C16: =C15/C6 -> -0.013475778 | D16: =D15/D6 -> 0.10505095 | E16: =E15/E6 -> 0.16333035 | F16: =F15/F6 -> 0.14507752 | G16: =G15/G6 -> 0.17579872 | H16: =H15/H6 -> 0.1908705 | I16: =I15/I6 -> 0.20399169 | ... M16: =M15/M6 -> 0.20203257 | O16: =O15/O6 -> 0.075657757 | P16: =P15/P6 -> 0.18253252 | Q16: =Q15/Q6 -> 0.19249877
A17: Cumulative EBITDA (Rs Lakh) — funding need / cash generated | B17: =B15 -> -38.12744 | C17: =B17+C15 -> -41.281633 | D17: =C17+D15 -> 3.4882247 | E17: =D17+E15 -> 104.61946 | F17: =E17+F15 -> 229.31485 | G17: =F17+G15 -> 411.83035 | H17: =G17+H15 -> 644.31466 | I17: =H17+I15 -> 920.25738 | J17: =I17+J15 -> 1190.7129 | ... M17: =L17+M15 -> 2209.318
A19: MEMO: VALUE CREATED BY THE ML ANALYTICS LAYER
A20: Memo: EBITDA excluding ML-layer benefits (baseline, no analytics) | B20: =B8-Volume_Build!B40-B13-B14 -> -41.792 | C20: =C8-Volume_Build!C40-C13-C14 -> -9.41896 | D20: =D8-Volume_Build!D40-D13-D14 -> 34.087784 | E20: =E8-Volume_Build!E40-E13-E14 -> 87.281047 | F20: =F8-Volume_Build!F40-F13-F14 -> 105.84929 | G20: =G8-Volume_Build!G40-G13-G14 -> 161.51301 | H20: =H8-Volume_Build!H40-H13-H14 -> 208.05206 | I20: =I8-Volume_Build!I40-I13-I14 -> 249.88214 | ... M20: =M8-Volume_Build!M40-M13-M14 -> 337.55693 | O20: =SUM(B20:E20) -> 70.157871 | P20: =SUM(F20:I20) -> 725.29649 | Q20: =SUM(J20:M20) -> 1161.7111
A21: Memo: Incremental EBITDA from ML analytics layer (SLA-breach + LTV models) | B21: =B15-B20 -> 3.66456 | C21: =C15-C20 -> 6.2647668 | D21: =D15-D20 -> 10.682074 | E21: =E15-E20 -> 13.850185 | F21: =F15-F20 -> 18.846104 | G21: =G15-G20 -> 21.002487 | H21: =H15-H20 -> 24.432254 | I21: =I15-I20 -> 26.060586 | ... M21: =M15-M20 -> 34.494502 | O21: =SUM(B21:E21) -> 34.461586 | P21: =SUM(F21:I21) -> 90.341431 | Q21: =SUM(J21:M21) -> 127.34954

Sheet DCF_Valuation
A1: DCF & VALUATION : DELHIVERY DIRECT (C2C) INITIATIVE
A2: Is the FPDR led GTM strategy proposed in the case NPV positive on a standalone basis?
A4: 1. FREE CASH FLOW BUILD (Rs Lakh)
A5: Metric | B5: Year 1 | C5: Year 2 | D5: Year 3 | E5: Terminal
A6: Revenue | B6: =PnL!O6 -> 1382.7988 | C6: =PnL!P6 -> 4468.4526 | D6: =PnL!Q6 -> 6696.4616
A7: EBITDA | B7: =PnL!O15 -> 104.61946 | C7: =PnL!P15 -> 815.63792 | D7: =PnL!Q15 -> 1289.0606
A8: Less: Tax (on positive EBITDA only) | B8: =MAX(0,B7)*Assumptions!$B$12 -> 26.154864 | C8: =MAX(0,C7)*Assumptions!$B$12 -> 203.90948 | D8: =MAX(0,D7)*Assumptions!$B$12 -> 322.26515
A9: Less: Maintenance capex (% of revenue) | B9: =B6*Assumptions!$B$13 -> 27.655976 | C9: =C6*Assumptions!$B$13 -> 89.369052 | D9: =D6*Assumptions!$B$13 -> 133.92923
A10: Free cash flow (FCF) | B10: =B7-B8-B9 -> 50.808617 | C10: =C7-C8-C9 -> 522.35939 | D10: =D7-D8-D9 -> 832.86623
A11: Terminal value (perpetuity on Yr-3 FCF) | E11: =D10*(1+Assumptions!$B$11)/(Assumptions!$B$10-Assumptions!$B$11) -> 9716.7727
A13: 2. DISCOUNTING & NPV
A14: Metric | B14: Year 1 | C14: Year 2 | D14: Year 3 | E14: Terminal (in Yr 3)
A15: Discount factor @ WACC | B15: =1/(1+Assumptions!$B$10)^1 -> 0.87719298 | C15: =1/(1+Assumptions!$B$10)^2 -> 0.76946753 | D15: =1/(1+Assumptions!$B$10)^3 -> 0.67497152 | E15: =1/(1+Assumptions!$B$10)^3 -> 0.67497152
A16: PV of FCF / Terminal value | B16: =B10*B15 -> 44.568962 | C16: =C10*C15 -> 401.93859 | D16: =D10*D15 -> 562.16098 | E16: =E11*E15 -> 6558.5448
A17: NPV of the initiative (Rs Lakh) | B17: =SUM(B16:D16)+E16 -> 7567.2133
A18: NPV of the initiative (Rs Crore) | B18: =B17/100 -> 75.672133
A20: 3. FUNDING NEED, BREAK-EVEN & IRR
A21: Peak funding need before breakeven (Rs Lakh) | B21: =-MIN(PnL!B17:M17,0) -> 41.281633
A22: Break-even quarter (of 12) | B22: =COUNTIF(PnL!B17:M17,"<0")+1 -> 3
A23: Cash flow series for IRR: Year 0 (investment) | B23: =-B21 -> -41.281633
A24: Year 1 / Year 2 / Year 3 (incl. terminal value) | B24: =B10 -> 50.808617 | C24: =C10 -> 522.35939 | D24: =D10+E11 -> 10549.639
A25: Project IRR (3-year + terminal value) | B25: =IRR(B23:D24) -> 6.4840555
A26: IRR cashflow series: Year0 = -(peak cumulative funding need), Year1-3 = FCF (Year 3 incl. terminal value)

Sheet Sensitivity
A1: SENSITIVITY ANALYSIS
A2: How fragile is the case's economics to churn, CAC and cost of capital assumptions?
A4: 1. LTV : CAC SENSITIVITY : HOMEPRENEURS / SOCIAL SELLERS (primary FPDR entry segment)
A5: Monthly retention -> | B5: 0.8 | C5: 0.85 | D5: 0.9 | E5: 0.93 | F5: 0.95
A6: CAC (Rs) (rows)
A7: 250 | B7: =(Assumptions!$B$17*Assumptions!$B$20)/(1-B$5/(1+LTV_Model!$S$1))/A7 -> 5.0601928 | C7: =(Assumptions!$B$17*Assumptions!$B$20)/(1-C$5/(1+LTV_Model!$S$1))/A7 -> 6.6318877 | D7: =(Assumptions!$B$17*Assumptions!$B$20)/(1-D$5/(1+LTV_Model!$S$1))/A7 -> 9.6197938 | E7: =(Assumptions!$B$17*Assumptions!$B$20)/(1-E$5/(1+LTV_Model!$S$1))/A7 -> 13.183611 | F7: =(Assumptions!$B$17*Assumptions!$B$20)/(1-F$5/(1+LTV_Model!$S$1))/A7 -> 17.507605
A8: 300 | B8: =(Assumptions!$B$17*Assumptions!$B$20)/(1-B$5/(1+LTV_Model!$S$1))/A8 -> 4.2168273 | C8: =(Assumptions!$B$17*Assumptions!$B$20)/(1-C$5/(1+LTV_Model!$S$1))/A8 -> 5.5265731 | D8: =(Assumptions!$B$17*Assumptions!$B$20)/(1-D$5/(1+LTV_Model!$S$1))/A8 -> 8.0164948 | E8: =(Assumptions!$B$17*Assumptions!$B$20)/(1-E$5/(1+LTV_Model!$S$1))/A8 -> 10.986342 | F8: =(Assumptions!$B$17*Assumptions!$B$20)/(1-F$5/(1+LTV_Model!$S$1))/A8 -> 14.589671
A9: 350 | B9: =(Assumptions!$B$17*Assumptions!$B$20)/(1-B$5/(1+LTV_Model!$S$1))/A9 -> 3.6144234 | C9: =(Assumptions!$B$17*Assumptions!$B$20)/(1-C$5/(1+LTV_Model!$S$1))/A9 -> 4.7370626 | D9: =(Assumptions!$B$17*Assumptions!$B$20)/(1-D$5/(1+LTV_Model!$S$1))/A9 -> 6.8712813 | E9: =(Assumptions!$B$17*Assumptions!$B$20)/(1-E$5/(1+LTV_Model!$S$1))/A9 -> 9.4168649 | F9: =(Assumptions!$B$17*Assumptions!$B$20)/(1-F$5/(1+LTV_Model!$S$1))/A9 -> 12.505432
A10: 400 | B10: =(Assumptions!$B$17*Assumptions!$B$20)/(1-B$5/(1+LTV_Model!$S$1))/A10 -> 3.1626205 | C10: =(Assumptions!$B$17*Assumptions!$B$20)/(1-C$5/(1+LTV_Model!$S$1))/A10 -> 4.1449298 | D10: =(Assumptions!$B$17*Assumptions!$B$20)/(1-D$5/(1+LTV_Model!$S$1))/A10 -> 6.0123711 | E10: =(Assumptions!$B$17*Assumptions!$B$20)/(1-E$5/(1+LTV_Model!$S$1))/A10 -> 8.2397568 | F10: =(Assumptions!$B$17*Assumptions!$B$20)/(1-F$5/(1+LTV_Model!$S$1))/A10 -> 10.942253
A11: 450 | B11: =(Assumptions!$B$17*Assumptions!$B$20)/(1-B$5/(1+LTV_Model!$S$1))/A11 -> 2.8112182 | C11: =(Assumptions!$B$17*Assumptions!$B$20)/(1-C$5/(1+LTV_Model!$S$1))/A11 -> 3.6843821 | D11: =(Assumptions!$B$17*Assumptions!$B$20)/(1-D$5/(1+LTV_Model!$S$1))/A11 -> 5.3443299 | E11: =(Assumptions!$B$17*Assumptions!$B$20)/(1-E$5/(1+LTV_Model!$S$1))/A11 -> 7.3242282 | F11: =(Assumptions!$B$17*Assumptions!$B$20)/(1-F$5/(1+LTV_Model!$S$1))/A11 -> 9.7264474
A13: Cell = closed-form LTV(retention) / CAC. Base case (90% retention, Rs350 CAC) sits at the centre ( highlighted below)
A15: 2. NPV SENSITIVITY (Rs Lakh) : WACC vs TERMINAL GROWTH
A16: WACC (rows) / Terminal growth (cols) -> | B16: 0.03 | C16: 0.04 | D16: 0.05 | E16: 0.06 | F16: 0.07
A17: 0.1 | B17: =DCF_Valuation!$B$10/(1+$A17)+DCF_Valuation!$C$10/(1+$A17)^2+DCF_Valuation!$D$10/(1+$A17)^3+(DCF_Valuation!$D$10*(1+B$16)/($A17-B$16))/(1+$A17)^3 -> 10311.023 | C17: =DCF_Valuation!$B$10/(1+$A17)+DCF_Valuation!$C$10/(1+$A17)^2+DCF_Valuation!$D$10/(1+$A17)^3+(DCF_Valuation!$D$10*(1+C$16)/($A17-C$16))/(1+$A17)^3 -> 11949.878 | D17: =DCF_Valuation!$B$10/(1+$A17)+DCF_Valuation!$C$10/(1+$A17)^2+DCF_Valuation!$D$10/(1+$A17)^3+(DCF_Valuation!$D$10*(1+D$16)/($A17-D$16))/(1+$A17)^3 -> 14244.276 | E17: =DCF_Valuation!$B$10/(1+$A17)+DCF_Valuation!$C$10/(1+$A17)^2+DCF_Valuation!$D$10/(1+$A17)^3+(DCF_Valuation!$D$10*(1+E$16)/($A17-E$16))/(1+$A17)^3 -> 17685.872 | F17: =DCF_Valuation!$B$10/(1+$A17)+DCF_Valuation!$C$10/(1+$A17)^2+DCF_Valuation!$D$10/(1+$A17)^3+(DCF_Valuation!$D$10*(1+F$16)/($A17-F$16))/(1+$A17)^3 -> 23421.865
A18: 0.12 | B18: =DCF_Valuation!$B$10/(1+$A18)+DCF_Valuation!$C$10/(1+$A18)^2+DCF_Valuation!$D$10/(1+$A18)^3+(DCF_Valuation!$D$10*(1+B$16)/($A18-B$16))/(1+$A18)^3 -> 7839.0739 | C18: =DCF_Valuation!$B$10/(1+$A18)+DCF_Valuation!$C$10/(1+$A18)^2+DCF_Valuation!$D$10/(1+$A18)^3+(DCF_Valuation!$D$10*(1+C$16)/($A18-C$16))/(1+$A18)^3 -> 8761.2348 | D18: =DCF_Valuation!$B$10/(1+$A18)+DCF_Valuation!$C$10/(1+$A18)^2+DCF_Valuation!$D$10/(1+$A18)^3+(DCF_Valuation!$D$10*(1+D$16)/($A18-D$16))/(1+$A18)^3 -> 9946.8702 | E18: =DCF_Valuation!$B$10/(1+$A18)+DCF_Valuation!$C$10/(1+$A18)^2+DCF_Valuation!$D$10/(1+$A18)^3+(DCF_Valuation!$D$10*(1+E$16)/($A18-E$16))/(1+$A18)^3 -> 11527.718 | F18: =DCF_Valuation!$B$10/(1+$A18)+DCF_Valuation!$C$10/(1+$A18)^2+DCF_Valuation!$D$10/(1+$A18)^3+(DCF_Valuation!$D$10*(1+F$16)/($A18-F$16))/(1+$A18)^3 -> 13740.904
A19: 0.14 | B19: =DCF_Valuation!$B$10/(1+$A19)+DCF_Valuation!$C$10/(1+$A19)^2+DCF_Valuation!$D$10/(1+$A19)^3+(DCF_Valuation!$D$10*(1+B$16)/($A19-B$16))/(1+$A19)^3 -> 6272.5395 | C19: =DCF_Valuation!$B$10/(1+$A19)+DCF_Valuation!$C$10/(1+$A19)^2+DCF_Valuation!$D$10/(1+$A19)^3+(DCF_Valuation!$D$10*(1+C$16)/($A19-C$16))/(1+$A19)^3 -> 6855.1427 | D19: =DCF_Valuation!$B$10/(1+$A19)+DCF_Valuation!$C$10/(1+$A19)^2+DCF_Valuation!$D$10/(1+$A19)^3+(DCF_Valuation!$D$10*(1+D$16)/($A19-D$16))/(1+$A19)^3 -> 7567.2133 | E19: =DCF_Valuation!$B$10/(1+$A19)+DCF_Valuation!$C$10/(1+$A19)^2+DCF_Valuation!$D$10/(1+$A19)^3+(DCF_Valuation!$D$10*(1+E$16)/($A19-E$16))/(1+$A19)^3 -> 8457.3015 | F19: =DCF_Valuation!$B$10/(1+$A19)+DCF_Valuation!$C$10/(1+$A19)^2+DCF_Valuation!$D$10/(1+$A19)^3+(DCF_Valuation!$D$10*(1+F$16)/($A19-F$16))/(1+$A19)^3 -> 9601.7007
A20: 0.16 | B20: =DCF_Valuation!$B$10/(1+$A20)+DCF_Valuation!$C$10/(1+$A20)^2+DCF_Valuation!$D$10/(1+$A20)^3+(DCF_Valuation!$D$10*(1+B$16)/($A20-B$16))/(1+$A20)^3 -> 5193.1931 | C20: =DCF_Valuation!$B$10/(1+$A20)+DCF_Valuation!$C$10/(1+$A20)^2+DCF_Valuation!$D$10/(1+$A20)^3+(DCF_Valuation!$D$10*(1+C$16)/($A20-C$16))/(1+$A20)^3 -> 5589.9593 | D20: =DCF_Valuation!$B$10/(1+$A20)+DCF_Valuation!$C$10/(1+$A20)^2+DCF_Valuation!$D$10/(1+$A20)^3+(DCF_Valuation!$D$10*(1+D$16)/($A20-D$16))/(1+$A20)^3 -> 6058.8649 | E20: =DCF_Valuation!$B$10/(1+$A20)+DCF_Valuation!$C$10/(1+$A20)^2+DCF_Valuation!$D$10/(1+$A20)^3+(DCF_Valuation!$D$10*(1+E$16)/($A20-E$16))/(1+$A20)^3 -> 6621.5515 | F20: =DCF_Valuation!$B$10/(1+$A20)+DCF_Valuation!$C$10/(1+$A20)^2+DCF_Valuation!$D$10/(1+$A20)^3+(DCF_Valuation!$D$10*(1+F$16)/($A20-F$16))/(1+$A20)^3 -> 7309.2796
A21: 0.18 | B21: =DCF_Valuation!$B$10/(1+$A21)+DCF_Valuation!$C$10/(1+$A21)^2+DCF_Valuation!$D$10/(1+$A21)^3+(DCF_Valuation!$D$10*(1+B$16)/($A21-B$16))/(1+$A21)^3 -> 4405.8856 | C21: =DCF_Valuation!$B$10/(1+$A21)+DCF_Valuation!$C$10/(1+$A21)^2+DCF_Valuation!$D$10/(1+$A21)^3+(DCF_Valuation!$D$10*(1+C$16)/($A21-C$16))/(1+$A21)^3 -> 4690.7197 | D21: =DCF_Valuation!$B$10/(1+$A21)+DCF_Valuation!$C$10/(1+$A21)^2+DCF_Valuation!$D$10/(1+$A21)^3+(DCF_Valuation!$D$10*(1+D$16)/($A21-D$16))/(1+$A21)^3 -> 5019.3744 | E21: =DCF_Valuation!$B$10/(1+$A21)+DCF_Valuation!$C$10/(1+$A21)^2+DCF_Valuation!$D$10/(1+$A21)^3+(DCF_Valuation!$D$10*(1+E$16)/($A21-E$16))/(1+$A21)^3 -> 5402.8048 | F21: =DCF_Valuation!$B$10/(1+$A21)+DCF_Valuation!$C$10/(1+$A21)^2+DCF_Valuation!$D$10/(1+$A21)^3+(DCF_Valuation!$D$10*(1+F$16)/($A21-F$16))/(1+$A21)^3 -> 5855.95
A23: Base case (WACC 14%, terminal growth 5%) reconciles to DCF_Valuation!B17(NPV).
A25: 3. WHAT-IF: MARKETING EFFICIENCY OF THE LTV MODEL
A26: CAC efficiency gain assumed | B26: 0 | C26: 0.06 | D26: 0.12 | E26: 0.18 | F26: 0.24
A27: Resulting 3-yr EBITDA (Rs Lakh) | B27: =PnL!$O$15+PnL!$P$15+PnL!$Q$15+(B26-Assumptions!$B$37)*(Volume_Build!$B$40+Volume_Build!$C$40+Volume_Build!$D$40+Volume_Build!$E$40+Volume_Build!$F$40+Volume_Build!$G$40+Volume_Build!$H$40+Volume_Build!$I$40+Volume_Build!$J$40+Volume_Build!$K$40+Volume_Build!$L$40+Volume_Build!$M$40) -> 2107.738 | C27: =PnL!$O$15+PnL!$P$15+PnL!$Q$15+(C26-Assumptions!$B$37)*(Volume_Build!$B$40+Volume_Build!$C$40+Volume_Build!$D$40+Volume_Build!$E$40+Volume_Build!$F$40+Volume_Build!$G$40+Volume_Build!$H$40+Volume_Build!$I$40+Volume_Build!$J$40+Volume_Build!$K$40+Volume_Build!$L$40+Volume_Build!$M$40) -> 2158.528 | D27: =PnL!$O$15+PnL!$P$15+PnL!$Q$15+(D26-Assumptions!$B$37)*(Volume_Build!$B$40+Volume_Build!$C$40+Volume_Build!$D$40+Volume_Build!$E$40+Volume_Build!$F$40+Volume_Build!$G$40+Volume_Build!$H$40+Volume_Build!$I$40+Volume_Build!$J$40+Volume_Build!$K$40+Volume_Build!$L$40+Volume_Build!$M$40) -> 2209.318 | E27: =PnL!$O$15+PnL!$P$15+PnL!$Q$15+(E26-Assumptions!$B$37)*(Volume_Build!$B$40+Volume_Build!$C$40+Volume_Build!$D$40+Volume_Build!$E$40+Volume_Build!$F$40+Volume_Build!$G$40+Volume_Build!$H$40+Volume_Build!$I$40+Volume_Build!$J$40+Volume_Build!$K$40+Volume_Build!$L$40+Volume_Build!$M$40) -> 2260.108 | F27: =PnL!$O$15+PnL!$P$15+PnL!$Q$15+(F26-Assumptions!$B$37)*(Volume_Build!$B$40+Volume_Build!$C$40+Volume_Build!$D$40+Volume_Build!$E$40+Volume_Build!$F$40+Volume_Build!$G$40+Volume_Build!$H$40+Volume_Build!$I$40+Volume_Build!$J$40+Volume_Build!$K$40+Volume_Build!$L$40+Volume_Build!$M$40) -> 2310.898
A29: Shows 3-yr EBITDA if the LTV-model-driven CAC efficiency gain differs from the 12% base case; illustrates the $ stake of the ML platform's targeting quality.

Sheet Dashboard
A1: EXECUTIVE DASHBOARD : DELHIVERY DIRECT (C2C) FINANCIAL CASE
A4: HEADLINE RESULTS (3 YR HORIZON)
B5: 3-yr cumulative revenue (Rs Cr) | C5: =(PnL!$O$6+PnL!$P$6+PnL!$Q$6)/100 -> 125.47713 | E5: Project NPV (Rs Cr, base case) | F5: =DCF_Valuation!$B$18 -> 75.672133
B6: 3-yr cumulative EBITDA (Rs Cr) | C6: =PnL!$M$17/100 -> 22.09318 | E6: Project IRR (3-yr + terminal) | F6: =DCF_Valuation!$B$25 -> 6.4840555
B7: Break-even quarter (of 12) | C7: =DCF_Valuation!$B$22 -> 3 | E7: Blended LTV:CAC : Homepreneurs | F7: =LTV_Model!$B$46 -> 6.7667964
B8: Peak funding need (Rs Cr) | C8: =DCF_Valuation!$B$21/100 -> 0.41281633 | E8: Blended LTV:CAC : C2C Marketplace | F8: =LTV_Model!$L$46 -> 0.19425411
A10: SEGMENT ECONOMICS AT A GLANCE (from FPDR framework)
B11: Segment | C11: LTV (Rs, 36mo) | D11: CAC (Rs) | E11: LTV:CAC | F11: Payback (mo)
B12: Homepreneurs / Social Sellers | C12: =LTV_Model!B43 -> 2368.3787 | D12: =LTV_Model!B45 -> 350 | E12: =LTV_Model!B46 -> 6.7667964 | F12: =LTV_Model!B47 -> 0
B13: Students & Migrants | C13: =LTV_Model!G43 -> 195.05707 | D13: =LTV_Model!G45 -> 150 | E13: =LTV_Model!G46 -> 1.3003804 | F13: =LTV_Model!G47 -> 2
B14: C2C Marketplace Sellers | C14: =LTV_Model!L43 -> 42.735904 | D14: =LTV_Model!L45 -> 220 | E14: =LTV_Model!L46 -> 0.19425411 | F14: =LTV_Model!L47 -> 35
A16: VALUE CREATED BY THE ML ANALYTICS LAYER (LTV / delay / SLA-breach models)
B17: 3-yr incremental EBITDA from ML layer (Rs Cr) | C17: =(PnL!$O$21+PnL!$P$21+PnL!$Q$21)/100 -> 2.5215256
B18: of which: claims-cost avoided (SLA-breach model) | C18: =(PnL!$O$9+PnL!$P$9+PnL!$Q$9)/100 -> 1.5057256
B19: of which: CAC saved via LTV-model targeting (Rs Cr, approx.) | C19: =Assumptions!$B$37*(Volume_Build!$B$40+Volume_Build!$C$40+Volume_Build!$D$40+Volume_Build!$E$40+Volume_Build!$F$40+Volume_Build!$G$40+Volume_Build!$H$40+Volume_Build!$I$40+Volume_Build!$J$40+Volume_Build!$K$40+Volume_Build!$L$40+Volume_Build!$M$40)/100 -> 1.0158
B24: Quarter | C24: Cumulative EBITDA (Rs Lakh) | E24: Segment | F24: 3-yr Revenue (Rs Lakh)
B25: Q1 | C25: =PnL!B17 -> -38.12744 | E25: Homepreneurs / Social Sellers | F25: =SUM(Volume_Build!B10:M10) -> 11823.542
B26: Q2 | C26: =PnL!C17 -> -41.281633 | E26: Students & Migrants | F26: =SUM(Volume_Build!B19:M19) -> 609.30678
B27: Q3 | C27: =PnL!D17 -> 3.4882247 | E27: C2C Marketplace Sellers | F27: =SUM(Volume_Build!B28:M28) -> 114.86414
B28: Q4 | C28: =PnL!E17 -> 104.61946
B29: Q5 | C29: =PnL!F17 -> 229.31485
B30: Q6 | C30: =PnL!G17 -> 411.83035
B31: Q7 | C31: =PnL!H17 -> 644.31466
B32: Q8 | C32: =PnL!I17 -> 920.25738
B33: Q9 | C33: =PnL!J17 -> 1190.7129
B34: Q10 | C34: =PnL!K17 -> 1497.0092
B35: Q11 | C35: =PnL!L17 -> 1837.2666
B36: Q12 | C36: =PnL!M17 -> 2209.318
